coguard_cli/__init__.py
coguard_cli/__main__.py
coguard_cli/api_connection.py
coguard_cli/check_common_util.py
coguard_cli/cluster_rule_fail_util.py
coguard_cli/docker_dao.py
coguard_cli/print_colors.py
coguard_cli/util.py
coguard_cli/additional_scan_results/__init__.py
coguard_cli/auth/__init__.py
coguard_cli/auth/auth_config.py
coguard_cli/auth/enums.py
coguard_cli/auth/token.py
coguard_cli/auth/util.py
coguard_cli/ci_cd/__init__.py
coguard_cli/ci_cd/ci_cd_provider_abc.py
coguard_cli/ci_cd/ci_cd_provider_factory.py
coguard_cli/ci_cd/ci_cd_providers/__init__.py
coguard_cli/ci_cd/ci_cd_providers/ci_cd_provider_github.py
coguard_cli/ci_cd/ci_cd_scripts/github/github_coguard_action.yml
coguard_cli/cloud_scan/__init__.py
coguard_cli/discovery/__init__.py
coguard_cli/discovery/config_file_finder_abc.py
coguard_cli/discovery/config_file_finder_factory.py
coguard_cli/discovery/additional_scan_results/__init__.py
coguard_cli/discovery/additional_scan_results/additional_scan_result_factory.py
coguard_cli/discovery/additional_scan_results/additional_scan_result_producer_abc.py
coguard_cli/discovery/additional_scan_results/phpstan_scan_result_producer.py
coguard_cli/discovery/additional_scan_results/trivy_sbom_scanning_result_producer.py
coguard_cli/discovery/cloud_discovery/__init__.py
coguard_cli/discovery/cloud_discovery/cloud_provider_abc.py
coguard_cli/discovery/cloud_discovery/cloud_provider_factory.py
coguard_cli/discovery/cloud_discovery/cloud_providers/__init__.py
coguard_cli/discovery/cloud_discovery/cloud_providers/cloud_provider_aws.py
coguard_cli/discovery/cloud_discovery/cloud_providers/cloud_provider_azure.py
coguard_cli/discovery/cloud_discovery/cloud_providers/cloud_provider_gcp.py
coguard_cli/discovery/cloud_discovery/terraformer_extract_image_helper/Dockerfile
coguard_cli/discovery/cloud_discovery/terraformer_extract_image_helper/data/versions.tf
coguard_cli/discovery/cloud_discovery/terraformer_extract_image_helper/scripts/cmd_for_dfile
coguard_cli-0.3.10.dist-info/licenses/LICENSE
coguard_cli-0.3.10.dist-info/METADATA
coguard_cli-0.3.10.dist-info/WHEEL
coguard_cli-0.3.10.dist-info/entry_points.txt
coguard_cli-0.3.10.dist-info/top_level.txt
coguard_cli-0.3.10.dist-info/RECORD
