Metadata-Version: 2.4
Name: coguard-cli
Version: 0.3.10
Summary: A command line interface for scanning configuration files with CoGuard
Home-page: https://github.com/coguardio/coguard-cli
Author: Heinle Solutions Inc.
Author-email: albert@coguard.io
Project-URL: Bug Tracker, https://github.com/coguardio/coguard-cli/issues
Classifier: Programming Language :: Python :: 3
Classifier: License :: OSI Approved :: MIT License
Classifier: Operating System :: OS Independent
Requires-Python: >=3.7
License-File: LICENSE
Requires-Dist: requests
Requires-Dist: setuptools
Requires-Dist: jwt
Requires-Dist: pyyaml
Requires-Dist: flatten-dict
Requires-Dist: python-hcl2
Requires-Dist: boto3
Requires-Dist: cfn-flip
Dynamic: license-file
